Metadata-Version: 2.4
Name: test-worker
Version: 1.0.0a41
Summary: Python Language Worker for Azure Functions Runtime
Author-email: "Azure Functions team at Microsoft Corp." <azurefunctions@microsoft.com>
License:     MIT License
Project-URL: Documentation, https://github.com/Azure/azure-functions-python-worker?tab=readme-ov-file#-azure-functions-python-worker
Project-URL: Repository, https://github.com/Azure/azure-functions-python-worker
Keywords: azure,functions,azurefunctions,python,serverless
Classifier: Development Status :: 5 - Production/Stable
Classifier: Programming Language :: Python
Classifier: Programming Language :: Python :: 3
Classifier: Programming Language :: Python :: 3.13
Classifier: Operating System :: Microsoft :: Windows
Classifier: Operating System :: POSIX
Classifier: Operating System :: MacOS :: MacOS X
Classifier: Environment :: Web Environment
Classifier: License :: OSI Approved :: MIT License
Classifier: Intended Audience :: Developers
Requires-Python: >=3.11
License-File: LICENSE
Requires-Dist: azurefunctions-extensions-base; python_version >= "3.8"
Requires-Dist: azure-functions
Provides-Extra: dev
Requires-Dist: azure-eventhub; extra == "dev"
Requires-Dist: azure-functions-durable; extra == "dev"
Requires-Dist: azure-monitor-opentelemetry; python_version >= "3.8" and extra == "dev"
Requires-Dist: flask; extra == "dev"
Requires-Dist: fastapi~=0.103.2; extra == "dev"
Requires-Dist: pydantic; extra == "dev"
Requires-Dist: pycryptodome==3.*; extra == "dev"
Requires-Dist: flake8==5.*; python_version == "3.7" and extra == "dev"
Requires-Dist: flake8==6.*; python_version >= "3.8" and extra == "dev"
Requires-Dist: mypy; extra == "dev"
Requires-Dist: pytest; extra == "dev"
Requires-Dist: requests==2.*; extra == "dev"
Requires-Dist: coverage; extra == "dev"
Requires-Dist: grpcio~=1.70.0; extra == "dev"
Requires-Dist: grpcio-tools~=1.70.0; extra == "dev"
Requires-Dist: pytest-sugar; extra == "dev"
Requires-Dist: opentelemetry-api; python_version >= "3.8" and extra == "dev"
Requires-Dist: pytest-cov; extra == "dev"
Requires-Dist: pytest-xdist; extra == "dev"
Requires-Dist: pytest-randomly; extra == "dev"
Requires-Dist: pytest-instafail; extra == "dev"
Requires-Dist: pytest-rerunfailures; extra == "dev"
Requires-Dist: ptvsd; extra == "dev"
Requires-Dist: python-dotenv; extra == "dev"
Requires-Dist: plotly; extra == "dev"
Requires-Dist: scikit-learn; extra == "dev"
Requires-Dist: opencv-python; extra == "dev"
Requires-Dist: pandas; extra == "dev"
Requires-Dist: numpy; extra == "dev"
Requires-Dist: pre-commit; extra == "dev"
Requires-Dist: invoke; extra == "dev"
Provides-Extra: test-http-v2
Requires-Dist: azurefunctions-extensions-http-fastapi==1.0.0b2; extra == "test-http-v2"
Requires-Dist: ujson; extra == "test-http-v2"
Requires-Dist: orjson; extra == "test-http-v2"
Provides-Extra: test-deferred-bindings
Requires-Dist: azurefunctions-extensions-bindings-blob==1.0.0b3; extra == "test-deferred-bindings"
Dynamic: license-file
